Metadata-Version: 2.4
Name: mseep-mcp-image-placeholder
Version: 0.1.4
Summary: MCP Image Placeholder Server
Author-email: mseep <support@skydeck.ai>
Requires-Python: >=3.12
License-File: LICENSE
Requires-Dist: mcp[cli]>=1.2.1
Dynamic: license-file
